{
  "customerNumber": 112,
  "orders": [
    {
      "orderNumber": 10124,
      "orderDate": "2003-05-21",
      "requiredDate": "2003-05-29",
      "shippedDate": "2003-05-25",
      "status": "Shipped",
      "comments": "Customer very concerned about the exact color of the models. There is high risk that he may dispute the order because there is a slight color mismatch",
      "customerNumber": 112,
      "details": [
        {
          "orderLineNumber": 1,
          "productName": "1938 Cadillac V-16 Presidential Limousine",
          "productCode": "S24_2022",
          "priceEach": 36.29,
          "quantityOrdered": 22,
          "lineTotal": 798.38
        },
        {
          "orderLineNumber": 2,
          "productName": "1939 Chevrolet Deluxe Coupe",
          "productCode": "S24_1937",
          "priceEach": 30.53,
          "quantityOrdered": 45,
          "lineTotal": 1373.85
        },
        {
          "orderLineNumber": 3,
          "productName": "1932 Model A Ford J-Coupe",
          "productCode": "S18_2325",
          "priceEach": 111.87,
          "quantityOrdered": 42,
          "lineTotal": 4698.54
        },
        {
          "orderLineNumber": 4,
          "productName": "1936 Mercedes Benz 500k Roadster",
          "productCode": "S24_3969",
          "priceEach": 36.11,
          "quantityOrdered": 46,
          "lineTotal": 1661.06
        },
        {
          "orderLineNumber": 5,
          "productName": "1911 Ford Town Car",
          "productCode": "S18_2248",
          "priceEach": 58.12,
          "quantityOrdered": 42,
          "lineTotal": 2441.04
        },
        {
          "orderLineNumber": 6,
          "productName": "1917 Grand Touring Sedan",
          "productCode": "S18_1749",
          "priceEach": 153.0,
          "quantityOrdered": 21,
          "lineTotal": 3213.0
        },
        {
          "orderLineNumber": 7,
          "productName": "1932 Alfa Romeo 8C2300 Spider Sport",
          "productCode": "S18_4409",
          "priceEach": 75.46,
          "quantityOrdered": 36,
          "lineTotal": 2716.56
        },
        {
          "orderLineNumber": 8,
          "productName": "1957 Ford Thunderbird",
          "productCode": "S18_4933",
          "priceEach": 66.28,
          "quantityOrdered": 23,
          "lineTotal": 1524.44
        },
        {
          "orderLineNumber": 9,
          "productName": "1952 Citroen-15CV",
          "productCode": "S24_2887",
          "priceEach": 93.95,
          "quantityOrdered": 25,
          "lineTotal": 2348.75
        },
        {
          "orderLineNumber": 10,
          "productName": "1949 Jaguar XK 120",
          "productCode": "S24_2766",
          "priceEach": 74.51,
          "quantityOrdered": 32,
          "lineTotal": 2384.32
        },
        {
          "orderLineNumber": 11,
          "productName": "1969 Chevrolet Camaro Z28",
          "productCode": "S24_3191",
          "priceEach": 76.19,
          "quantityOrdered": 49,
          "lineTotal": 3733.31
        },
        {
          "orderLineNumber": 12,
          "productName": "1970 Chevy Chevelle SS 454",
          "productCode": "S24_1046",
          "priceEach": 62.47,
          "quantityOrdered": 22,
          "lineTotal": 1374.34
        },
        {
          "orderLineNumber": 13,
          "productName": "2002 Chevy Corvette",
          "productCode": "S24_3432",
          "priceEach": 101.73,
          "quantityOrdered": 43,
          "lineTotal": 4374.39
        }
      ]
    },
    {
      "orderNumber": 10278,
      "orderDate": "2004-08-06",
      "requiredDate": "2004-08-16",
      "shippedDate": "2004-08-09",
      "status": "Shipped",
      "comments": null,
      "customerNumber": 112,
      "details": [
        {
          "orderLineNumber": 1,
          "productName": "1966 Shelby Cobra 427 S/C",
          "productCode": "S24_1628",
          "priceEach": 48.8,
          "quantityOrdered": 35,
          "lineTotal": 1708.0
        },
        {
          "orderLineNumber": 2,
          "productName": "1965 Aston Martin DB5",
          "productCode": "S18_1589",
          "priceEach": 107.02,
          "quantityOrdered": 23,
          "lineTotal": 2461.46
        },
        {
          "orderLineNumber": 3,
          "productName": "1999 Indy 500 Monte Carlo SS",
          "productCode": "S18_2870",
          "priceEach": 117.48,
          "quantityOrdered": 39,
          "lineTotal": 4581.72
        },
        {
          "orderLineNumber": 4,
          "productName": "1948 Porsche Type 356 Roadster",
          "productCode": "S18_3685",
          "priceEach": 114.44,
          "quantityOrdered": 31,
          "lineTotal": 3547.64
        },
        {
          "orderLineNumber": 5,
          "productName": "1995 Honda Civic",
          "productCode": "S18_1984",
          "priceEach": 118.07,
          "quantityOrdered": 29,
          "lineTotal": 3424.03
        },
        {
          "orderLineNumber": 6,
          "productName": "1993 Mazda RX-7",
          "productCode": "S18_1129",
          "priceEach": 114.65,
          "quantityOrdered": 34,
          "lineTotal": 3898.1
        },
        {
          "orderLineNumber": 7,
          "productName": "1992 Ferrari 360 Spider red",
          "productCode": "S18_3232",
          "priceEach": 167.65,
          "quantityOrdered": 42,
          "lineTotal": 7041.3
        },
        {
          "orderLineNumber": 8,
          "productName": "1982 Lamborghini Diablo",
          "productCode": "S24_2972",
          "priceEach": 37.38,
          "quantityOrdered": 31,
          "lineTotal": 1158.78
        },
        {
          "orderLineNumber": 9,
          "productName": "1956 Porsche 356A Coupe",
          "productCode": "S24_3856",
          "priceEach": 136.22,
          "quantityOrdered": 25,
          "lineTotal": 3405.5
        },
        {
          "orderLineNumber": 10,
          "productName": "1948 Porsche 356-A Roadster",
          "productCode": "S18_1889",
          "priceEach": 73.15,
          "quantityOrdered": 29,
          "lineTotal": 2121.35
        }
      ]
    },
    {
      "orderNumber": 10346,
      "orderDate": "2004-11-29",
      "requiredDate": "2004-12-05",
      "shippedDate": "2004-11-30",
      "status": "Shipped",
      "comments": null,
      "customerNumber": 112,
      "details": [
        {
          "orderLineNumber": 1,
          "productName": "1949 Jaguar XK 120",
          "productCode": "S24_2766",
          "priceEach": 87.24,
          "quantityOrdered": 25,
          "lineTotal": 2181.0
        },
        {
          "orderLineNumber": 2,
          "productName": "1969 Chevrolet Camaro Z28",
          "productCode": "S24_3191",
          "priceEach": 80.47,
          "quantityOrdered": 24,
          "lineTotal": 1931.28
        },
        {
          "orderLineNumber": 3,
          "productName": "1937 Lincoln Berline",
          "productCode": "S18_1342",
          "priceEach": 88.36,
          "quantityOrdered": 42,
          "lineTotal": 3711.12
        },
        {
          "orderLineNumber": 4,
          "productName": "1936 Mercedes Benz 500k Roadster",
          "productCode": "S24_3969",
          "priceEach": 38.57,
          "quantityOrdered": 22,
          "lineTotal": 848.54
        },
        {
          "orderLineNumber": 5,
          "productName": "1952 Citroen-15CV",
          "productCode": "S24_2887",
          "priceEach": 117.44,
          "quantityOrdered": 24,
          "lineTotal": 2818.56
        },
        {
          "orderLineNumber": 6,
          "productName": "2002 Chevy Corvette",
          "productCode": "S24_3432",
          "priceEach": 103.87,
          "quantityOrdered": 26,
          "lineTotal": 2700.62
        }
      ]
    }
  ]
}