{
  "customerNumber": 320,
  "orders": [
    {
      "orderNumber": 10143,
      "orderDate": "2003-08-10",
      "requiredDate": "2003-08-18",
      "shippedDate": "2003-08-12",
      "status": "Shipped",
      "comments": "Can we deliver the new Ford Mustang models by end-of-quarter?",
      "customerNumber": 320,
      "details": [
        {
          "orderLineNumber": 1,
          "productName": "1930 Buick Marquette Phaeton",
          "productCode": "S50_1341",
          "priceEach": 34.91,
          "quantityOrdered": 34,
          "lineTotal": 1186.94
        },
        {
          "orderLineNumber": 2,
          "productName": "American Airlines: B767-300",
          "productCode": "S700_1691",
          "priceEach": 86.77,
          "quantityOrdered": 36,
          "lineTotal": 3123.72
        },
        {
          "orderLineNumber": 3,
          "productName": "F/A 18 Hornet 1/72",
          "productCode": "S700_3167",
          "priceEach": 70.4,
          "quantityOrdered": 28,
          "lineTotal": 1971.2
        },
        {
          "orderLineNumber": 4,
          "productName": "America West Airlines B757-200",
          "productCode": "S700_2466",
          "priceEach": 79.78,
          "quantityOrdered": 26,
          "lineTotal": 2074.28
        },
        {
          "orderLineNumber": 5,
          "productName": "American Airlines: MD-11S",
          "productCode": "S700_4002",
          "priceEach": 65.15,
          "quantityOrdered": 34,
          "lineTotal": 2215.1
        },
        {
          "orderLineNumber": 6,
          "productName": "Corsair F4U ( Bird Cage)",
          "productCode": "S24_3949",
          "priceEach": 55.96,
          "quantityOrdered": 28,
          "lineTotal": 1566.88
        },
        {
          "orderLineNumber": 7,
          "productName": "1980s Black Hawk Helicopter",
          "productCode": "S18_1662",
          "priceEach": 126.15,
          "quantityOrdered": 32,
          "lineTotal": 4036.8
        },
        {
          "orderLineNumber": 8,
          "productName": "1900s Vintage Bi-Plane",
          "productCode": "S24_2841",
          "priceEach": 63.71,
          "quantityOrdered": 27,
          "lineTotal": 1720.17
        },
        {
          "orderLineNumber": 9,
          "productName": "1937 Horch 930V Limousine",
          "productCode": "S24_3420",
          "priceEach": 59.83,
          "quantityOrdered": 33,
          "lineTotal": 1974.39
        },
        {
          "orderLineNumber": 10,
          "productName": "Boeing X-32A JSF",
          "productCode": "S72_1253",
          "priceEach": 49.66,
          "quantityOrdered": 37,
          "lineTotal": 1837.42
        },
        {
          "orderLineNumber": 11,
          "productName": "HMS Bounty",
          "productCode": "S700_2047",
          "priceEach": 87.8,
          "quantityOrdered": 26,
          "lineTotal": 2282.8
        },
        {
          "orderLineNumber": 12,
          "productName": "1941 Chevrolet Special Deluxe Cabriolet",
          "productCode": "S18_3856",
          "priceEach": 99.52,
          "quantityOrdered": 34,
          "lineTotal": 3383.68
        },
        {
          "orderLineNumber": 13,
          "productName": "1999 Yamaha Speed Boat",
          "productCode": "S18_3029",
          "priceEach": 70.54,
          "quantityOrdered": 46,
          "lineTotal": 3244.84
        },
        {
          "orderLineNumber": 14,
          "productName": "1940 Ford Delivery Sedan",
          "productCode": "S24_3816",
          "priceEach": 74.64,
          "quantityOrdered": 23,
          "lineTotal": 1716.72
        },
        {
          "orderLineNumber": 15,
          "productName": "1972 Alfa Romeo GTA",
          "productCode": "S10_4757",
          "priceEach": 133.28,
          "quantityOrdered": 49,
          "lineTotal": 6530.72
        },
        {
          "orderLineNumber": 16,
          "productName": "The USS Constitution Ship",
          "productCode": "S700_2610",
          "priceEach": 69.39,
          "quantityOrdered": 31,
          "lineTotal": 2151.09
        }
      ]
    },
    {
      "orderNumber": 10185,
      "orderDate": "2003-11-14",
      "requiredDate": "2003-11-21",
      "shippedDate": "2003-11-20",
      "status": "Shipped",
      "comments": null,
      "customerNumber": 320,
      "details": [
        {
          "orderLineNumber": 1,
          "productName": "The USS Constitution Ship",
          "productCode": "S700_2610",
          "priceEach": 61.44,
          "quantityOrdered": 39,
          "lineTotal": 2396.16
        },
        {
          "orderLineNumber": 2,
          "productName": "1912 Ford Model T Delivery Wagon",
          "productCode": "S24_3151",
          "priceEach": 83.2,
          "quantityOrdered": 33,
          "lineTotal": 2745.6
        },
        {
          "orderLineNumber": 3,
          "productName": "The Schooner Bluenose",
          "productCode": "S700_1138",
          "priceEach": 64.67,
          "quantityOrdered": 21,
          "lineTotal": 1358.07
        },
        {
          "orderLineNumber": 4,
          "productName": "The Titanic",
          "productCode": "S700_3505",
          "priceEach": 99.17,
          "quantityOrdered": 37,
          "lineTotal": 3669.29
        },
        {
          "orderLineNumber": 5,
          "productName": "The Queen Mary",
          "productCode": "S700_3962",
          "priceEach": 93.35,
          "quantityOrdered": 22,
          "lineTotal": 2053.7
        },
        {
          "orderLineNumber": 6,
          "productName": "Pont Yacht",
          "productCode": "S72_3212",
          "priceEach": 47.5,
          "quantityOrdered": 28,
          "lineTotal": 1330.0
        },
        {
          "orderLineNumber": 7,
          "productName": "18th century schooner",
          "productCode": "S24_2011",
          "priceEach": 105.69,
          "quantityOrdered": 30,
          "lineTotal": 3170.7
        },
        {
          "orderLineNumber": 8,
          "productName": "1904 Buick Runabout",
          "productCode": "S18_4522",
          "priceEach": 87.77,
          "quantityOrdered": 47,
          "lineTotal": 4125.19
        },
        {
          "orderLineNumber": 9,
          "productName": "1903 Ford Model A",
          "productCode": "S18_3140",
          "priceEach": 124.3,
          "quantityOrdered": 28,
          "lineTotal": 3480.4
        },
        {
          "orderLineNumber": 10,
          "productName": "The Mayflower",
          "productCode": "S700_1938",
          "priceEach": 79.68,
          "quantityOrdered": 30,
          "lineTotal": 2390.4
        },
        {
          "orderLineNumber": 11,
          "productName": "Collectable Wooden Train",
          "productCode": "S18_3259",
          "priceEach": 94.79,
          "quantityOrdered": 49,
          "lineTotal": 4644.71
        },
        {
          "orderLineNumber": 12,
          "productName": "1969 Ford Falcon",
          "productCode": "S12_3891",
          "priceEach": 147.07,
          "quantityOrdered": 43,
          "lineTotal": 6324.01
        },
        {
          "orderLineNumber": 13,
          "productName": "2001 Ferrari Enzo",
          "productCode": "S12_1108",
          "priceEach": 195.33,
          "quantityOrdered": 21,
          "lineTotal": 4101.93
        },
        {
          "orderLineNumber": 14,
          "productName": "1969 Corvair Monza",
          "productCode": "S12_3148",
          "priceEach": 146.55,
          "quantityOrdered": 33,
          "lineTotal": 4836.15
        },
        {
          "orderLineNumber": 15,
          "productName": "1962 City of Detroit Streetcar",
          "productCode": "S50_1514",
          "priceEach": 46.86,
          "quantityOrdered": 20,
          "lineTotal": 937.2
        },
        {
          "orderLineNumber": 16,
          "productName": "1970 Triumph Spitfire",
          "productCode": "S18_4027",
          "priceEach": 127.82,
          "quantityOrdered": 39,
          "lineTotal": 4984.98
        }
      ]
    },
    {
      "orderNumber": 10365,
      "orderDate": "2005-01-07",
      "requiredDate": "2005-01-18",
      "shippedDate": "2005-01-11",
      "status": "Shipped",
      "comments": null,
      "customerNumber": 320,
      "details": [
        {
          "orderLineNumber": 1,
          "productName": "1993 Mazda RX-7",
          "productCode": "S18_1129",
          "priceEach": 116.06,
          "quantityOrdered": 30,
          "lineTotal": 3481.8
        },
        {
          "orderLineNumber": 2,
          "productName": "2002 Yamaha YZR M1",
          "productCode": "S50_4713",
          "priceEach": 68.34,
          "quantityOrdered": 44,
          "lineTotal": 3006.96
        },
        {
          "orderLineNumber": 3,
          "productName": "1974 Ducati 350 Mk3 Desmo",
          "productCode": "S32_4485",
          "priceEach": 82.66,
          "quantityOrdered": 22,
          "lineTotal": 1818.52
        }
      ]
    }
  ]
}