{
  "customerNumber": 324,
  "orders": [
    {
      "orderNumber": 10129,
      "orderDate": "2003-06-12",
      "requiredDate": "2003-06-18",
      "shippedDate": "2003-06-14",
      "status": "Shipped",
      "comments": null,
      "customerNumber": 324,
      "details": [
        {
          "orderLineNumber": 1,
          "productName": "1940 Ford Delivery Sedan",
          "productCode": "S24_3816",
          "priceEach": 76.31,
          "quantityOrdered": 50,
          "lineTotal": 3815.5
        },
        {
          "orderLineNumber": 2,
          "productName": "1972 Alfa Romeo GTA",
          "productCode": "S10_4757",
          "priceEach": 123.76,
          "quantityOrdered": 33,
          "lineTotal": 4084.08
        },
        {
          "orderLineNumber": 3,
          "productName": "The USS Constitution Ship",
          "productCode": "S700_2610",
          "priceEach": 72.28,
          "quantityOrdered": 45,
          "lineTotal": 3252.6
        },
        {
          "orderLineNumber": 4,
          "productName": "1912 Ford Model T Delivery Wagon",
          "productCode": "S24_3151",
          "priceEach": 81.43,
          "quantityOrdered": 41,
          "lineTotal": 3338.63
        },
        {
          "orderLineNumber": 5,
          "productName": "The Schooner Bluenose",
          "productCode": "S700_1138",
          "priceEach": 58.67,
          "quantityOrdered": 31,
          "lineTotal": 1818.77
        },
        {
          "orderLineNumber": 6,
          "productName": "The Titanic",
          "productCode": "S700_3505",
          "priceEach": 90.15,
          "quantityOrdered": 42,
          "lineTotal": 3786.3
        },
        {
          "orderLineNumber": 7,
          "productName": "The Queen Mary",
          "productCode": "S700_3962",
          "priceEach": 94.34,
          "quantityOrdered": 30,
          "lineTotal": 2830.2
        },
        {
          "orderLineNumber": 8,
          "productName": "Pont Yacht",
          "productCode": "S72_3212",
          "priceEach": 44.23,
          "quantityOrdered": 32,
          "lineTotal": 1415.36
        },
        {
          "orderLineNumber": 9,
          "productName": "18th century schooner",
          "productCode": "S24_2011",
          "priceEach": 113.06,
          "quantityOrdered": 45,
          "lineTotal": 5087.7
        }
      ]
    },
    {
      "orderNumber": 10175,
      "orderDate": "2003-11-06",
      "requiredDate": "2003-11-14",
      "shippedDate": "2003-11-09",
      "status": "Shipped",
      "comments": null,
      "customerNumber": 324,
      "details": [
        {
          "orderLineNumber": 1,
          "productName": "1957 Chevy Pickup",
          "productCode": "S12_4473",
          "priceEach": 109.02,
          "quantityOrdered": 26,
          "lineTotal": 2834.52
        },
        {
          "orderLineNumber": 2,
          "productName": "1958 Chevy Corvette Limited Edition",
          "productCode": "S24_2840",
          "priceEach": 32.18,
          "quantityOrdered": 37,
          "lineTotal": 1190.66
        },
        {
          "orderLineNumber": 3,
          "productName": "1954 Greyhound Scenicruiser",
          "productCode": "S32_2509",
          "priceEach": 50.86,
          "quantityOrdered": 50,
          "lineTotal": 2543.0
        },
        {
          "orderLineNumber": 4,
          "productName": "1964 Mercedes Tour Bus",
          "productCode": "S18_2319",
          "priceEach": 101.87,
          "quantityOrdered": 48,
          "lineTotal": 4889.76
        },
        {
          "orderLineNumber": 5,
          "productName": "1992 Ferrari 360 Spider red",
          "productCode": "S18_3232",
          "priceEach": 150.71,
          "quantityOrdered": 29,
          "lineTotal": 4370.59
        },
        {
          "orderLineNumber": 6,
          "productName": "1962 Volkswagen Microbus",
          "productCode": "S24_2300",
          "priceEach": 121.4,
          "quantityOrdered": 28,
          "lineTotal": 3399.2
        },
        {
          "orderLineNumber": 7,
          "productName": "1926 Ford Fire Engine",
          "productCode": "S18_2432",
          "priceEach": 59.55,
          "quantityOrdered": 41,
          "lineTotal": 2441.55
        },
        {
          "orderLineNumber": 8,
          "productName": "1980\u2019s GM Manhattan Express",
          "productCode": "S32_1268",
          "priceEach": 89.57,
          "quantityOrdered": 22,
          "lineTotal": 1970.54
        },
        {
          "orderLineNumber": 9,
          "productName": "1962 LanciaA Delta 16V",
          "productCode": "S10_4962",
          "priceEach": 119.67,
          "quantityOrdered": 33,
          "lineTotal": 3949.11
        },
        {
          "orderLineNumber": 10,
          "productName": "1940s Ford truck",
          "productCode": "S18_4600",
          "priceEach": 102.92,
          "quantityOrdered": 47,
          "lineTotal": 4837.24
        },
        {
          "orderLineNumber": 11,
          "productName": "1982 Camaro Z28",
          "productCode": "S700_2824",
          "priceEach": 80.92,
          "quantityOrdered": 42,
          "lineTotal": 3398.64
        },
        {
          "orderLineNumber": 12,
          "productName": "1996 Peterbilt 379 Stake Bed with Outrigger",
          "productCode": "S32_3522",
          "priceEach": 56.24,
          "quantityOrdered": 29,
          "lineTotal": 1630.96
        }
      ]
    },
    {
      "orderNumber": 10351,
      "orderDate": "2004-12-03",
      "requiredDate": "2004-12-11",
      "shippedDate": "2004-12-07",
      "status": "Shipped",
      "comments": null,
      "customerNumber": 324,
      "details": [
        {
          "orderLineNumber": 1,
          "productName": "1980s Black Hawk Helicopter",
          "productCode": "S18_1662",
          "priceEach": 143.5,
          "quantityOrdered": 39,
          "lineTotal": 5596.5
        },
        {
          "orderLineNumber": 2,
          "productName": "1941 Chevrolet Special Deluxe Cabriolet",
          "productCode": "S18_3856",
          "priceEach": 104.81,
          "quantityOrdered": 20,
          "lineTotal": 2096.2
        },
        {
          "orderLineNumber": 3,
          "productName": "Corsair F4U ( Bird Cage)",
          "productCode": "S24_3949",
          "priceEach": 68.24,
          "quantityOrdered": 34,
          "lineTotal": 2320.16
        },
        {
          "orderLineNumber": 4,
          "productName": "1937 Horch 930V Limousine",
          "productCode": "S24_3420",
          "priceEach": 53.92,
          "quantityOrdered": 38,
          "lineTotal": 2048.96
        },
        {
          "orderLineNumber": 5,
          "productName": "1900s Vintage Bi-Plane",
          "productCode": "S24_2841",
          "priceEach": 64.4,
          "quantityOrdered": 25,
          "lineTotal": 1610.0
        }
      ]
    }
  ]
}