{
  "customerNumber": 398,
  "orders": [
    {
      "orderNumber": 10258,
      "orderDate": "2004-06-15",
      "requiredDate": "2004-06-25",
      "shippedDate": "2004-06-23",
      "status": "Shipped",
      "comments": null,
      "customerNumber": 398,
      "details": [
        {
          "orderLineNumber": 1,
          "productName": "1982 Camaro Z28",
          "productCode": "S700_2824",
          "priceEach": 86.99,
          "quantityOrdered": 45,
          "lineTotal": 3914.55
        },
        {
          "orderLineNumber": 2,
          "productName": "1996 Peterbilt 379 Stake Bed with Outrigger",
          "productCode": "S32_3522",
          "priceEach": 62.7,
          "quantityOrdered": 20,
          "lineTotal": 1254.0
        },
        {
          "orderLineNumber": 3,
          "productName": "1958 Setra Bus",
          "productCode": "S12_1666",
          "priceEach": 133.94,
          "quantityOrdered": 41,
          "lineTotal": 5491.54
        },
        {
          "orderLineNumber": 4,
          "productName": "1939 Cadillac Limousine",
          "productCode": "S18_4668",
          "priceEach": 49.81,
          "quantityOrdered": 21,
          "lineTotal": 1046.01
        },
        {
          "orderLineNumber": 5,
          "productName": "1940 Ford Pickup Truck",
          "productCode": "S18_1097",
          "priceEach": 113.17,
          "quantityOrdered": 41,
          "lineTotal": 4639.97
        },
        {
          "orderLineNumber": 6,
          "productName": "1952 Alpine Renault 1300",
          "productCode": "S10_1949",
          "priceEach": 177.87,
          "quantityOrdered": 32,
          "lineTotal": 5691.84
        }
      ]
    },
    {
      "orderNumber": 10339,
      "orderDate": "2004-11-23",
      "requiredDate": "2004-11-30",
      "shippedDate": "2004-11-30",
      "status": "Shipped",
      "comments": null,
      "customerNumber": 398,
      "details": [
        {
          "orderLineNumber": 1,
          "productName": "1936 Harley Davidson El Knucklehead",
          "productCode": "S18_2625",
          "priceEach": 48.46,
          "quantityOrdered": 30,
          "lineTotal": 1453.8
        },
        {
          "orderLineNumber": 2,
          "productName": "P-51-D Mustang",
          "productCode": "S18_2581",
          "priceEach": 79.41,
          "quantityOrdered": 27,
          "lineTotal": 2144.07
        },
        {
          "orderLineNumber": 3,
          "productName": "2003 Harley-Davidson Eagle Drag Bike",
          "productCode": "S10_4698",
          "priceEach": 178.17,
          "quantityOrdered": 39,
          "lineTotal": 6948.63
        },
        {
          "orderLineNumber": 4,
          "productName": "1996 Moto Guzzi 1100i",
          "productCode": "S10_2016",
          "priceEach": 117.75,
          "quantityOrdered": 40,
          "lineTotal": 4710.0
        },
        {
          "orderLineNumber": 5,
          "productName": "The Schooner Bluenose",
          "productCode": "S700_1138",
          "priceEach": 53.34,
          "quantityOrdered": 22,
          "lineTotal": 1173.48
        },
        {
          "orderLineNumber": 6,
          "productName": "Boeing X-32A JSF",
          "productCode": "S72_1253",
          "priceEach": 49.66,
          "quantityOrdered": 27,
          "lineTotal": 1340.82
        },
        {
          "orderLineNumber": 7,
          "productName": "1928 British Royal Navy Airplane",
          "productCode": "S24_1785",
          "priceEach": 106.14,
          "quantityOrdered": 21,
          "lineTotal": 2228.94
        },
        {
          "orderLineNumber": 8,
          "productName": "American Airlines: MD-11S",
          "productCode": "S700_4002",
          "priceEach": 66.63,
          "quantityOrdered": 50,
          "lineTotal": 3331.5
        },
        {
          "orderLineNumber": 9,
          "productName": "The USS Constitution Ship",
          "productCode": "S700_2610",
          "priceEach": 62.16,
          "quantityOrdered": 50,
          "lineTotal": 3108.0
        },
        {
          "orderLineNumber": 10,
          "productName": "1997 BMW R 1100 S",
          "productCode": "S24_1578",
          "priceEach": 96.92,
          "quantityOrdered": 27,
          "lineTotal": 2616.84
        },
        {
          "orderLineNumber": 11,
          "productName": "Corsair F4U ( Bird Cage)",
          "productCode": "S24_3949",
          "priceEach": 57.32,
          "quantityOrdered": 45,
          "lineTotal": 2579.4
        },
        {
          "orderLineNumber": 12,
          "productName": "1900s Vintage Bi-Plane",
          "productCode": "S24_2841",
          "priceEach": 67.82,
          "quantityOrdered": 55,
          "lineTotal": 3730.1
        },
        {
          "orderLineNumber": 13,
          "productName": "1912 Ford Model T Delivery Wagon",
          "productCode": "S24_3151",
          "priceEach": 73.46,
          "quantityOrdered": 55,
          "lineTotal": 4040.3
        },
        {
          "orderLineNumber": 14,
          "productName": "1937 Horch 930V Limousine",
          "productCode": "S24_3420",
          "priceEach": 57.86,
          "quantityOrdered": 29,
          "lineTotal": 1677.94
        },
        {
          "orderLineNumber": 15,
          "productName": "HMS Bounty",
          "productCode": "S700_2047",
          "priceEach": 86.9,
          "quantityOrdered": 55,
          "lineTotal": 4779.5
        },
        {
          "orderLineNumber": 16,
          "productName": "1940 Ford Delivery Sedan",
          "productCode": "S24_3816",
          "priceEach": 72.96,
          "quantityOrdered": 42,
          "lineTotal": 3064.32
        }
      ]
    },
    {
      "orderNumber": 10372,
      "orderDate": "2005-01-26",
      "requiredDate": "2005-02-05",
      "shippedDate": "2005-01-28",
      "status": "Shipped",
      "comments": null,
      "customerNumber": 398,
      "details": [
        {
          "orderLineNumber": 1,
          "productName": "1969 Ford Falcon",
          "productCode": "S12_3891",
          "priceEach": 140.15,
          "quantityOrdered": 34,
          "lineTotal": 4765.1
        },
        {
          "orderLineNumber": 2,
          "productName": "The Mayflower",
          "productCode": "S700_1938",
          "priceEach": 74.48,
          "quantityOrdered": 44,
          "lineTotal": 3277.12
        },
        {
          "orderLineNumber": 3,
          "productName": "1903 Ford Model A",
          "productCode": "S18_3140",
          "priceEach": 131.13,
          "quantityOrdered": 28,
          "lineTotal": 3671.64
        },
        {
          "orderLineNumber": 4,
          "productName": "1969 Corvair Monza",
          "productCode": "S12_3148",
          "priceEach": 146.55,
          "quantityOrdered": 40,
          "lineTotal": 5862.0
        },
        {
          "orderLineNumber": 5,
          "productName": "Collectable Wooden Train",
          "productCode": "S18_3259",
          "priceEach": 91.76,
          "quantityOrdered": 25,
          "lineTotal": 2294.0
        },
        {
          "orderLineNumber": 6,
          "productName": "1970 Triumph Spitfire",
          "productCode": "S18_4027",
          "priceEach": 119.2,
          "quantityOrdered": 48,
          "lineTotal": 5721.6
        },
        {
          "orderLineNumber": 7,
          "productName": "1904 Buick Runabout",
          "productCode": "S18_4522",
          "priceEach": 78.99,
          "quantityOrdered": 41,
          "lineTotal": 3238.59
        },
        {
          "orderLineNumber": 8,
          "productName": "18th century schooner",
          "productCode": "S24_2011",
          "priceEach": 102.0,
          "quantityOrdered": 37,
          "lineTotal": 3774.0
        },
        {
          "orderLineNumber": 9,
          "productName": "1962 City of Detroit Streetcar",
          "productCode": "S50_1514",
          "priceEach": 56.82,
          "quantityOrdered": 24,
          "lineTotal": 1363.68
        }
      ]
    },
    {
      "orderNumber": 10408,
      "orderDate": "2005-04-22",
      "requiredDate": "2005-04-29",
      "shippedDate": "2005-04-27",
      "status": "Shipped",
      "comments": null,
      "customerNumber": 398,
      "details": [
        {
          "orderLineNumber": 1,
          "productName": "1936 Mercedes Benz 500k Roadster",
          "productCode": "S24_3969",
          "priceEach": 41.03,
          "quantityOrdered": 15,
          "lineTotal": 615.45
        }
      ]
    }
  ]
}